{
 "SoundBanksInfo": {
  "Platform": "Mac",
  "BasePlatform": "Mac",
  "SchemaVersion": "16",
  "SoundBankVersion": "154",
  "SoundBanks": [
   {
    "Id": "2325531825",
    "Type": "Event",
    "GUID": "{AD2496BF-1D07-4623-8D6C-858A62B32249}",
    "Language": "English(US)",
    "Hash": "{EBB921D8-2378-9F07-7F7F-B1C1472DAD03}",
    "ObjectPath": "Play_TutorialDialog12",
    "ShortName": "Play_TutorialDialog12",
    "Path": "Event/English(US)/Play_TutorialDialog12.bnk",
    "Media": [
     {
      "Id": "481943279",
      "Language": "English(US)",
      "Streaming": "false",
      "Location": "Loose",
      "ShortName": "TutorialDialog12.wav",
      "Path": "Media/English(US)/481943279.wem",
      "CachePath": "16/{16D8E3C3-20C1-93A2-3A40-9E3C29CDAA55}.wem"
     }
    ],
    "Events": [
     {
      "Id": "2325531825",
      "Name": "Play_TutorialDialog12",
      "ObjectPath": "\\Events\\Default Work Unit\\Dialog\\Tutorial\\Play_TutorialDialog12",
      "GUID": "{AD2496BF-1D07-4623-8D6C-858A62B32249}",
      "DurationType": "OneShot",
      "DurationMin": "5.5",
      "DurationMax": "5.5",
      "MediaRefs": [
       {
        "Id": "481943279"
       }
      ]
     }
    ]
   }
  ],
  "FileHash": "{918981A4-7E5B-7EEA-7A0D-DF640B10EC60}"
 }
}